msgpickle.py
msgpickle-1.4.1.dist-info/METADATA
msgpickle-1.4.1.dist-info/WHEEL
msgpickle-1.4.1.dist-info/top_level.txt
msgpickle-1.4.1.dist-info/RECORD
